{"cameraMode":{"drawMode":0,"name":"Shaded","section":"Shading Mode"},"sceneLighting":false,"audioPlay":false,"sceneViewState":{"m_AlwaysRefresh":false,"showFog":true,"showSkybox":false,"showFlares":true,"showImageEffects":true,"showParticleSystems":true,"showVisualEffectGraphs":true,"m_FxEnabled":true},"in2DMode":false,"pivot":{"x":0.0,"y":0.0,"z":1.3373277187347413},"rotation":{"x":0.3291461169719696,"y":0.0014164646854624153,"z":-0.0004937583580613136,"w":0.9442819952964783},"size":8.247321128845215,"orthographic":false}